dg_sqlmesh/__init__.py
dg_sqlmesh/enhanced_context.py
dg_sqlmesh/execution_check_results.py
dg_sqlmesh/execution_notifier.py
dg_sqlmesh/execution_results_payload.py
dg_sqlmesh/execution_selection.py
dg_sqlmesh/factory.py
dg_sqlmesh/notifier.py
dg_sqlmesh/notifier_service.py
dg_sqlmesh/resource.py
dg_sqlmesh/simple_run_tracker.py
dg_sqlmesh/sqlmesh_asset_check_utils.py
dg_sqlmesh/sqlmesh_asset_execution_utils.py
dg_sqlmesh/sqlmesh_asset_utils.py
dg_sqlmesh/sqlmesh_schedule_utils.py
dg_sqlmesh/translator.py
dg_sqlmesh/components/sqlmesh_project/__init__.py
dg_sqlmesh/components/sqlmesh_project/component.py
dg_sqlmesh/components/sqlmesh_project/scaffolder.py
dg_sqlmesh-1.10.1.dist-info/licenses/LICENSE
dg_sqlmesh-1.10.1.dist-info/METADATA
dg_sqlmesh-1.10.1.dist-info/WHEEL
dg_sqlmesh-1.10.1.dist-info/entry_points.txt
dg_sqlmesh-1.10.1.dist-info/top_level.txt
dg_sqlmesh-1.10.1.dist-info/RECORD
