Metadata-Version: 2.4
Name: dg-sqlmesh
Version: 1.10.1
Summary: Seamless integration between Dagster and SQLMesh for modern data engineering workflows
Author-email: Thomas Trividic <thomastrividic@gmail.com>
License-Expression: Apache-2.0
Project-URL: Homepage, https://github.com/fosk06/dagster-sqlmesh
Project-URL: Repository, https://github.com/fosk06/dagster-sqlmesh
Project-URL: Documentation, https://github.com/fosk06/dagster-sqlmesh#readme
Project-URL: Issues, https://github.com/fosk06/dagster-sqlmesh/issues
Keywords: dagster,sqlmesh,data-engineering,etl,data-pipeline
Classifier: Development Status :: 4 - Beta
Classifier: Intended Audience :: Developers
Classifier: Programming Language :: Python :: 3
Classifier: Programming Language :: Python :: 3.11
Classifier: Programming Language :: Python :: 3.12
Classifier: Topic :: Database
Classifier: Topic :: Scientific/Engineering :: Information Analysis
Classifier: Topic :: Software Development :: Libraries :: Python Modules
Requires-Python: <3.13,>=3.11
License-File: LICENSE
Requires-Dist: dagster>=1.11.8
Requires-Dist: pandas>=2.2.1
Requires-Dist: sqlmesh[postgres,web]>=0.214.0
Requires-Dist: anyio>=4.9.0
Requires-Dist: vulture>=2.14
Requires-Dist: jinja2>=3.0.0
Provides-Extra: dev
Requires-Dist: dagster-webserver>=1.11.8; extra == "dev"
Requires-Dist: dagster-dg-cli>=1.11.8; extra == "dev"
Requires-Dist: pytest>=8.4.1; extra == "dev"
Dynamic: license-file
